japanese_personal_name_dataset/__init__.py
japanese_personal_name_dataset/api.py
japanese_personal_name_dataset/core.py
japanese_personal_name_dataset/helpers.py
japanese_personal_name_dataset/dataset/first_name_man_opti.csv
japanese_personal_name_dataset/dataset/first_name_man_org.csv
japanese_personal_name_dataset/dataset/first_name_woman_opti.csv
japanese_personal_name_dataset/dataset/first_name_woman_org.csv
japanese_personal_name_dataset/dataset/last_name_org.csv
japanese_personal_name_dataset-0.1.1.dist-info/METADATA
japanese_personal_name_dataset-0.1.1.dist-info/WHEEL
japanese_personal_name_dataset-0.1.1.dist-info/licenses/LICENSE
japanese_personal_name_dataset-0.1.1.dist-info/RECORD
