Metadata-Version: 2.4
Name: japanese-personal-name-dataset
Version: 0.1.1
Summary: A comprehensive dataset of Japanese personal names (first names and last names) with hiragana readings, romaji, and kanji variations
Project-URL: Homepage, https://github.com/shuheilocale/japanese-personal-name-dataset
Project-URL: Repository, https://github.com/shuheilocale/japanese-personal-name-dataset
Project-URL: Issues, https://github.com/shuheilocale/japanese-personal-name-dataset/issues
Author-email: shuheilocale <xxx@gmail.com>
License: MIT
License-File: LICENSE
Keywords: dataset,hiragana,japanese,kanji,names,romaji
Classifier: Development Status :: 4 - Beta
Classifier: Intended Audience :: Developers
Classifier: License :: OSI Approved :: MIT License
Classifier: Natural Language :: Japanese
Classifier: Programming Language :: Python :: 3
Classifier: Programming Language :: Python :: 3.8
Classifier: Programming Language :: Python :: 3.9
Classifier: Programming Language :: Python :: 3.10
Classifier: Programming Language :: Python :: 3.11
Classifier: Programming Language :: Python :: 3.12
Classifier: Topic :: Software Development :: Libraries :: Python Modules
Classifier: Topic :: Text Processing :: Linguistic
Requires-Python: >=3.8
Provides-Extra: dev
Requires-Dist: pytest-cov>=4.0.0; extra == 'dev'
Requires-Dist: pytest>=7.0.0; extra == 'dev'
